kncloudevents/__init__.py
kncloudevents/kncloudevents.py
kncloudevents-0.1.0.dist-info/AUTHORS.rst
kncloudevents-0.1.0.dist-info/LICENSE
kncloudevents-0.1.0.dist-info/METADATA
kncloudevents-0.1.0.dist-info/WHEEL
kncloudevents-0.1.0.dist-info/top_level.txt
kncloudevents-0.1.0.dist-info/RECORD
