Metadata-Version: 2.1
Name: kncloudevents
Version: 0.1.0
Summary: A HTTP server for listening to Knative Eventing messages
Home-page: https://github.com/elegantmonkeys/python-kncloudevents
Author: The Elegant Monkeys
Author-email: contact@elegantmonkeys.com
License: Apache Software License 2.0
Keywords: knative kubernetes cloudevents
Platform: UNKNOWN
Classifier: Development Status :: 4 - Beta
Classifier: Intended Audience :: Developers
Classifier: License :: OSI Approved :: Apache Software License
Classifier: Natural Language :: English
Classifier: Programming Language :: Python :: 3
Classifier: Programming Language :: Python :: 3.5
Classifier: Programming Language :: Python :: 3.6
Classifier: Programming Language :: Python :: 3.7
Requires-Dist: cloudevents (==0.2.3)
